{
  "name": "Kedasha Kerr",
  "email": "jwsmith@colostate.edu",
  "phone": "1999-2002",
  "summary": "Four years experience in early childhood development with a diverse background in the care of",
  "roles": [
    {
      "title": "",
      "company": "",
      "start": "1999",
      "end": "2002",
      "description": "in early childhood development with a diverse background in the care of\nspecial needs children and adults.\nAdult Care Experience\n\u2022 Determined work placement for 150 special needs adult clients.\n\u2022 Maintained client databases and records.\n\u2022 Coordinated client contact with local health care professionals on a monthly basis.\n\u2022 Managed 25 volunteer workers.\nChildcare Experience\n\u2022 Coordinated service assignments for 20 part-time counselors and 100 client families.\n\u2022 Oversaw daily activity and outing planning for 100 clients.\n\u2022 Assisted families of special needs clients with researching financial assistance and\nhealthcare.\n\u2022 Assisted teachers with managing daily classroom activities.\n\u2022 Oversaw daily and special student activities.\nEmployment History\n Counseling Supervisor, The Wesley Center, Little Rock, Arkansas.\n1997-1999 Client Specialist, Rainbow Special Care Center, Little Rock, Arkansas\n1996-1997 Teacher\u2019s Assistant, Cowell Elementary, Conway, Arkansas"
    }
  ],
  "contact": {
    "address": "2002 Front Range Way Fort Collins, CO 80525",
    "email": "jwsmith@colostate.edu",
    "phone": ""
  },
  "sections": {
    "Adult Care Experience": [
      "Determined work placement for 150 special needs adult clients.",
      "Maintained client databases and records.",
      "Coordinated client contact with local health care professionals on a monthly basis.",
      "Managed 25 volunteer workers.",
      "Coordinated service assignments for 20 part-time counselors and 100 client families.",
      "Oversaw daily activity and outing planning for 100 clients.",
      "Assisted families of special needs clients with researching financial assistance and",
      "Assisted teachers with managing daily classroom activities.",
      "Oversaw daily and special student activities.",
      "BS in Early Childhood Development (1999)",
      "BA in Elementary Education (1998)",
      "GPA (4.0 Scale): Early Childhood Development \u2013 3.8, Elementary Education \u2013 3.5,",
      "Dean\u2019s List, Chancellor\u2019s List"
    ],
    "Childcare Experience": [
      "Coordinated service assignments for 20 part-time counselors and 100 client families.",
      "Oversaw daily activity and outing planning for 100 clients.",
      "Assisted families of special needs clients with researching financial assistance and",
      "Assisted teachers with managing daily classroom activities.",
      "Oversaw daily and special student activities.",
      "BS in Early Childhood Development (1999)",
      "BA in Elementary Education (1998)",
      "GPA (4.0 Scale): Early Childhood Development \u2013 3.8, Elementary Education \u2013 3.5,",
      "Dean\u2019s List, Chancellor\u2019s List"
    ],
    "Employment History": [
      {
        "title": "Counseling Supervisor",
        "company": "The Wesley Center",
        "location": "Little Rock, Arkansas.",
        "start": "1999",
        "end": "2002"
      },
      {
        "title": "Client Specialist",
        "company": "Rainbow Special Care Center",
        "location": "Little Rock, Arkansas",
        "start": "1997",
        "end": "1999"
      },
      {
        "title": "Teacher\u2019s Assistant",
        "company": "Cowell Elementary",
        "location": "Conway, Arkansas",
        "start": "1996",
        "end": "1997"
      }
    ],
    "Education": [
      "BS in Early Childhood Development (1999)",
      "BA in Elementary Education (1998)",
      "GPA (4.0 Scale): Early Childhood Development \u2013 3.8, Elementary Education \u2013 3.5,",
      "Dean\u2019s List, Chancellor\u2019s List",
      "GPA (4.0 Scale): Early Childhood Development \u2013 3.8, Elementary Education \u2013 3.5,",
      "Dean\u2019s List, Chancellor\u2019s List",
      "Dean\u2019s List, Chancellor\u2019s List"
    ]
  }
}